nonebot_plugin_flo_jav/__init__.py
nonebot_plugin_flo_jav/config.py
nonebot_plugin_flo_jav/constants.py
nonebot_plugin_flo_jav/model/__init__.py
nonebot_plugin_flo_jav/model/AVInfo.py
nonebot_plugin_flo_jav/model/SourceCookie.py
nonebot_plugin_flo_jav/repository/__init__.py
nonebot_plugin_flo_jav/repository/AVInfoRepo.py
nonebot_plugin_flo_jav/repository/CookieRepo.py
nonebot_plugin_flo_jav/repository/RepoBase.py
nonebot_plugin_flo_jav/scraper/__init__.py
nonebot_plugin_flo_jav/scraper/Javbus.py
nonebot_plugin_flo_jav/scraper/ScraperBase.py
nonebot_plugin_flo_jav/scraper/ScraperManager.py
nonebot_plugin_flo_jav/src/nonebot_plugin_flo_jav/__init__.py
nonebot_plugin_flo_jav-0.1.1.dist-info/licenses/LICENSE
nonebot_plugin_flo_jav-0.1.1.dist-info/METADATA
nonebot_plugin_flo_jav-0.1.1.dist-info/WHEEL
nonebot_plugin_flo_jav-0.1.1.dist-info/RECORD
