Metadata-Version: 2.4
Name: nonebot-plugin-flo-jav
Version: 0.1.1
Summary: Florenz的JAV元数据查询插件。
License: GPL-3.0-or-later
License-File: LICENSE
Author: Florenz
Author-email: florenz@tju.edu.cn
Requires-Python: >=3.9, <4.0
Classifier: License :: OSI Approved :: GNU General Public License v3 or later (GPLv3+)
Classifier: Programming Language :: Python :: 3
Classifier: Programming Language :: Python :: 3.9
Classifier: Programming Language :: Python :: 3.10
Classifier: Programming Language :: Python :: 3.11
Classifier: Programming Language :: Python :: 3.12
Classifier: Programming Language :: Python :: 3.13
Classifier: Programming Language :: Python :: 3.14
Requires-Dist: curl-cffi (>=0.13.0)
Requires-Dist: nb-cli (>=1.5.0)
Requires-Dist: nonebot-adapter-onebot (>=2.4.6)
Requires-Dist: nonebot-plugin-alconna (>=0.59.4)
Requires-Dist: nonebot-plugin-localstore (>=0.7.4)
Requires-Dist: nonebot-plugin-uninfo (>=0.9.0)
Requires-Dist: nonebot2[fastapi,httpx,websockets] (>=2.4.4)
Requires-Dist: pip (>=25.3)
Requires-Dist: poetry-core (>=2.2.1)
Requires-Dist: setuptools (>=80.9.0)
Project-URL: Repository, https://github.com/Florenz0707/nonebot-plugin-flo-jav
